Metadata-Version: 2.1
Name: datastructureshh
Version: 1.0
Summary: A package for some common data structures
Author: Harris Hasnain
Author-email: harris.hasnain@ucalgary.ca
License: UNKNOWN
Platform: UNKNOWN
